LICENSE
MANIFEST.in
README.md
VERSION
requirements.txt
setup.py
texta_tools/exceptions.py
texta_tools/minio_wrapper.py
texta_tools/quality_validator.py
texta_tools/text_processor.py
texta_tools/text_splitter.py
texta_tools.egg-info/PKG-INFO
texta_tools.egg-info/SOURCES.txt
texta_tools.egg-info/dependency_links.txt
texta_tools.egg-info/requires.txt
texta_tools.egg-info/top_level.txt
texta_tools/models/gibberish_model.pki
texta_tools/stop_words/english.txt
texta_tools/stop_words/estonian.txt
texta_tools/stop_words/russian.txt