Metadata-Version: 2.1
Name: texta-tools
Version: 2.1.1
Summary: texta-tools
Home-page: https://git.texta.ee/texta/texta-tools-python
Author: TEXTA
Author-email: info@texta.ee
License: GPLv3
Platform: UNKNOWN
License-File: LICENSE
